cqd/__init__.py
cqd/core.py
cqd-0.1.1.dist-info/METADATA
cqd-0.1.1.dist-info/WHEEL
cqd-0.1.1.dist-info/licenses/LICENSE
cqd-0.1.1.dist-info/RECORD
