Metadata-Version: 2.4
Name: cqd
Version: 0.1.1
Summary: cqd - A colorful object attribute inspector
Project-URL: Homepage, https://github.com/rayking99/cqd
Project-URL: Bug Tracker, https://github.com/rayking99/cqd/issues
Author-email: Jason Pickup <therayking99@gmail.com>
License-File: LICENSE
Classifier: Development Status :: 4 - Beta
Classifier: Intended Audience :: Developers
Classifier: License :: OSI Approved :: MIT License
Classifier: Operating System :: OS Independent
Classifier: Programming Language :: Python :: 3
Classifier: Topic :: Software Development :: Debuggers
Requires-Python: >=3.6
